dbx_hpexts/__init__.py
dbx_hpexts/dbutilslike/__init__.py
dbx_hpexts/dbutilslike/dbutils.py
dbx_hpexts/dbutilsops/__init__.py
dbx_hpexts/dbutilsops/dbutilsops.py
dbx_hpexts/dfops/__init__.py
dbx_hpexts/dfops/dfops.py
dbx_hpexts/hcpvault/__init__.py
dbx_hpexts/hcpvault/hcpsecretsmanager.py
dbx_hpexts/sapp.py
dbx_hpexts-0.1.18.dist-info/LICENCE
dbx_hpexts-0.1.18.dist-info/METADATA
dbx_hpexts-0.1.18.dist-info/WHEEL
dbx_hpexts-0.1.18.dist-info/RECORD
