Metadata-Version: 2.1
Name: dbx-hpexts
Version: 0.1.18
Summary: Databricks helpers and extensions
Author: francisco javier larios
Author-email: fjlsoto@gmail.com
Requires-Python: >=3.10,<4.0
Classifier: Programming Language :: Python :: 3
Classifier: Programming Language :: Python :: 3.10
Classifier: Programming Language :: Python :: 3.11
Classifier: Programming Language :: Python :: 3.12
Requires-Dist: hcp-vault-secrets-wrapper (>=0.7.5,<0.8.0)
Requires-Dist: pyspark (>=4.0.0,<5.0.0)
